Metadata-Version: 1.2
Name: whats-my-name
Version: 2.0.0
Summary: Packaged version of WhatsMyName
Home-page: https://github.com/rpigu-i/WhatsMyNamePackage
Maintainer: WebBreacher
License: Creative Commons ShareAlike 4.0
Platform: UNKNOWN
